MANIFEST.in
setup.py
ate_spyder/LICENSE.txt
ate_spyder/README.md
ate_spyder/__init__.py
ate_spyder/plugin.py
ate_spyder/project.py
ate_spyder/widgets/__init__.py
ate_spyder/widgets/constants.py
ate_spyder/widgets/main_widget.py
ate_spyder/widgets/navigation.py
ate_spyder/widgets/plugin.py
ate_spyder/widgets/statusbar.py
ate_spyder/widgets/toolbar.py
ate_spyder/widgets/validation.py
ate_spyder/widgets/actions_on/__init__.py
ate_spyder/widgets/actions_on/device/DeviceItem.py
ate_spyder/widgets/actions_on/device/EditDeviceWizard.py
ate_spyder/widgets/actions_on/device/NewDeviceWizard.py
ate_spyder/widgets/actions_on/device/NewDeviceWizard.ui
ate_spyder/widgets/actions_on/device/ViewDeviceWizard.py
ate_spyder/widgets/actions_on/device/__init__.py
ate_spyder/widgets/actions_on/die/Constants.py
ate_spyder/widgets/actions_on/die/DieItem.py
ate_spyder/widgets/actions_on/die/DieWizard.py
ate_spyder/widgets/actions_on/die/DieWizard.ui
ate_spyder/widgets/actions_on/die/EditDieWizard.py
ate_spyder/widgets/actions_on/die/ViewDieWizard.py
ate_spyder/widgets/actions_on/die/__init__.py
ate_spyder/widgets/actions_on/documentation/BaseFolderStructureItem.py
ate_spyder/widgets/actions_on/documentation/Constants.py
ate_spyder/widgets/actions_on/documentation/DocumentationItem.py
ate_spyder/widgets/actions_on/documentation/DocumentationObserver.py
ate_spyder/widgets/actions_on/documentation/FileIcon.py
ate_spyder/widgets/actions_on/documentation/__init__.py
ate_spyder/widgets/actions_on/flow/__init__.py
ate_spyder/widgets/actions_on/flow/AC/__init__.py
ate_spyder/widgets/actions_on/flow/AC/acwizard.py
ate_spyder/widgets/actions_on/flow/DR/__init__.py
ate_spyder/widgets/actions_on/flow/DR/drwizard.py
ate_spyder/widgets/actions_on/flow/EC/__init__.py
ate_spyder/widgets/actions_on/flow/EC/ecwizard.py
ate_spyder/widgets/actions_on/flow/ELFR/__init__.py
ate_spyder/widgets/actions_on/flow/ELFR/elfrwizard.py
ate_spyder/widgets/actions_on/flow/ESD/__init__.py
semi_ate_spyder.egg-info/PKG-INFO
semi_ate_spyder.egg-info/SOURCES.txt
semi_ate_spyder.egg-info/dependency_links.txt
semi_ate_spyder.egg-info/entry_points.txt
semi_ate_spyder.egg-info/requires.txt
semi_ate_spyder.egg-info/top_level.txt